odoo/addons/base_recurrence/README.rst
odoo/addons/base_recurrence/__init__.py
odoo/addons/base_recurrence/__manifest__.py
odoo/addons/base_recurrence/i18n/base_recurrence.pot
odoo/addons/base_recurrence/i18n/it.po
odoo/addons/base_recurrence/i18n/pt_BR.po
odoo/addons/base_recurrence/models/__init__.py
odoo/addons/base_recurrence/models/recurrence_mixin.py
odoo/addons/base_recurrence/readme/CONTRIBUTORS.rst
odoo/addons/base_recurrence/readme/DESCRIPTION.rst
odoo/addons/base_recurrence/readme/USAGE.rst
odoo/addons/base_recurrence/static/description/icon.png
odoo/addons/base_recurrence/static/description/index.html
odoo/addons/base_recurrence/tests/__init__.py
odoo/addons/base_recurrence/tests/fake_model.py
odoo/addons/base_recurrence/tests/test_recurrence.py
odoo14_addon_base_recurrence-14.0.1.0.1.dev7.dist-info/METADATA
odoo14_addon_base_recurrence-14.0.1.0.1.dev7.dist-info/WHEEL
odoo14_addon_base_recurrence-14.0.1.0.1.dev7.dist-info/top_level.txt
odoo14_addon_base_recurrence-14.0.1.0.1.dev7.dist-info/RECORD
